LICENSE
MANIFEST.in
README.rst
setup.cfg
setup.py
aioslacker/__init__.py
aioslacker/compat.py
aioslacker.egg-info/PKG-INFO
aioslacker.egg-info/SOURCES.txt
aioslacker.egg-info/dependency_links.txt
aioslacker.egg-info/not-zip-safe
aioslacker.egg-info/requires.txt
aioslacker.egg-info/top_level.txt