Metadata-Version: 1.1
Name: aioslacker
Version: 0.0.11
Summary: slacker wrapper for asyncio
Home-page: https://github.com/aio-libs/aioslacker
Author: Victor Kovtun
Author-email: hellysmile@gmail.com
License: UNKNOWN
Keywords: slack,slacker,asyncio,aiohttp
Platform: UNKNOWN
Classifier: Development Status :: 5 - Production/Stable
Classifier: Intended Audience :: Developers
Classifier: License :: OSI Approved :: MIT License
Classifier: Operating System :: POSIX
Classifier: Operating System :: MacOS :: MacOS X
Classifier: Operating System :: Microsoft :: Windows
Classifier: Programming Language :: Python
Classifier: Programming Language :: Python :: 3
Classifier: Programming Language :: Python :: 3.4
Classifier: Programming Language :: Python :: 3.5
Classifier: Programming Language :: Python :: 3.6
